README.md
setup.py
scanphyslog2bids/__init__.py
scanphyslog2bids/core.py
scanphyslog2bids/tests.py
scanphyslog2bids/utils.py
scanphyslog2bids/version.py
scanphyslog2bids.egg-info/PKG-INFO
scanphyslog2bids.egg-info/SOURCES.txt
scanphyslog2bids.egg-info/dependency_links.txt
scanphyslog2bids.egg-info/entry_points.txt
scanphyslog2bids.egg-info/requires.txt
scanphyslog2bids.egg-info/top_level.txt
scanphyslog2bids/data/example_for_gradient_log.log
scanphyslog2bids/data/example_for_gradient_log.nii.gz
scanphyslog2bids/data/example_for_interpolation.log
scanphyslog2bids/data/example_for_interpolation.nii.gz
scanphyslog2bids/data/example_for_vol_markers.log
scanphyslog2bids/data/example_for_vol_markers.nii.gz