Metadata-Version: 2.1
Name: scanphyslog2bids
Version: 0.1
Summary: scanphyslog2bids: converts Philips physiology files to the BIDS-format
Home-page: https://github.com/lukassnoek/scanphyslog2bids
Author: Lukas Snoek
Author-email: lukassnoek@gmail.com
Maintainer: Lukas Snoek
Maintainer-email: lukassnoek@gmail.com
License: 3-clause BSD
Platform: OS Independent
Classifier: Development Status :: 3 - Alpha
Classifier: Environment :: Console
Classifier: Intended Audience :: Science/Research
Classifier: License :: OSI Approved :: MIT License
Classifier: Operating System :: OS Independent
Classifier: Programming Language :: Python
Classifier: Topic :: Scientific/Engineering
Requires: numpy
